Metadata-Version: 2.1
Name: bmi_dbseabed
Version: 0.1.0
Summary: Fetch ocean seabed datasets from the dbSEABED system https://instaar.colorado.edu/~jenkinsc/dbseabed/
Author-email: Tian Gan <jamy127@foxmail.com>, Chris Jenkins <jenkinsc0@gmail.com>
Maintainer-email: Tian Gan <jamy127@foxmail.com>
License: MIT
Project-URL: documentation, https://github.com/gantian127/bmi_dbseabed
Project-URL: homepage, https://github.com/gantian127/bmi_dbseabed
Project-URL: repository, https://github.com/gantian127/bmi_dbseabed
Keywords: BMI,Basic Model Interface,dbSEABED
Classifier: Development Status :: 4 - Beta
Classifier: Intended Audience :: Science/Research
Classifier: License :: OSI Approved :: MIT License
Classifier: Operating System :: OS Independent
Classifier: Programming Language :: Python :: 3 :: Only
Classifier: Programming Language :: Python :: 3.10
Classifier: Programming Language :: Python :: 3.11
Classifier: Programming Language :: Python :: 3.12
Classifier: Programming Language :: Python :: Implementation :: CPython
Classifier: Topic :: Scientific/Engineering :: Oceanography
Requires-Python: >=3.10
License-File: LICENSE.md
Requires-Dist: bmipy
Requires-Dist: click
Requires-Dist: netcdf4
Requires-Dist: numpy
Requires-Dist: owslib
Requires-Dist: pyyaml
Requires-Dist: requests
Requires-Dist: rioxarray
Requires-Dist: xarray
Provides-Extra: dev
Requires-Dist: nox; extra == "dev"
Provides-Extra: notebooks
Requires-Dist: jupyter; extra == "notebooks"
Requires-Dist: matplotlib; extra == "notebooks"
Requires-Dist: numpy; extra == "notebooks"
Provides-Extra: testing
Requires-Dist: nbmake; extra == "testing"
Requires-Dist: pytest; extra == "testing"
Requires-Dist: pytest-cov; extra == "testing"
